pocket_option/__init__.py
pocket_option/client.py
pocket_option/constants.py
pocket_option/contrib/__init__.py
pocket_option/contrib/candles.py
pocket_option/contrib/deals.py
pocket_option/errors.py
pocket_option/generated_client.py
pocket_option/middleware.py
pocket_option/middlewares.py
pocket_option/models.py
pocket_option/types.py
pocket_option/utils.py
pocket_option-0.1.4.dist-info/licenses/LICENSE
pocket_option-0.1.4.dist-info/METADATA
pocket_option-0.1.4.dist-info/WHEEL
pocket_option-0.1.4.dist-info/RECORD
