Metadata-Version: 2.4
Name: pocket-option
Version: 0.1.4
Summary: Async API client for Pocket Option platform
License-Expression: MIT
License-File: LICENSE
Keywords: pocket option,pocket-option,pocketoption,trading,binary options,options,finance,fintech,api,api client,trading bot,algorithmic trading,automated trading,websocket,websocket client,market data,quotes,forex,crypto trading,crypto,exchange,python client
Author: Yury "lordralinc" Yushmanov
Requires-Python: >=3.13
Classifier: Programming Language :: Python :: 3
Classifier: Programming Language :: Python :: 3.13
Classifier: Programming Language :: Python :: 3.14
Provides-Extra: ujson
Requires-Dist: aiohttp[speedups] (>=3.13.1,<4.0.0)
Requires-Dist: brotli (>=1.2.0,<2.0.0)
Requires-Dist: pydantic (>=2.12.3,<3.0.0)
Requires-Dist: python-socketio[asyncio-client] (>=5.14.2,<6.0.0)
Requires-Dist: pytz (>=2025.2,<2026.0)
Requires-Dist: ujson (>=5.11.0,<6.0.0) ; extra == "ujson"
Project-URL: Homepage, https://github.com/lordralinc/pocket_option
Project-URL: Issues, https://github.com/lordralinc/pocket_option/issues
Project-URL: Repository, https://github.com/lordralinc/pocket_option
